LICENSE
MANIFEST.in
README.rst
setup.cfg
setup.py
version.py
./python2-requirements.txt
./requirements.txt
./matrixprofile/cycore.pyx
./matrixprofile/algorithms/cympx.pyx
./matrixprofile/io/protobuf/proto_messages.proto
./peritus_matrixprofile.egg-info/SOURCES.txt
./peritus_matrixprofile.egg-info/dependency_links.txt
./peritus_matrixprofile.egg-info/requires.txt
./peritus_matrixprofile.egg-info/top_level.txt
./tests/mpx_ab_mpa.txt
./tests/mpx_ab_mpb.txt
./tests/mpx_ab_mpia.txt
./tests/mpx_ab_mpib.txt
./tests/mpx_mp.txt
./tests/mpx_mpi.txt
./tests/muinvn_mua.txt
./tests/muinvn_stda.txt
./tests/sampledata.txt
./tests/scrimp.mp.txt
./tests/scrimp.mpi.txt
./venv/lib/python3.8/site-packages/Babel-2.10.1.dist-info/entry_points.txt
./venv/lib/python3.8/site-packages/Babel-2.10.1.dist-info/top_level.txt
./venv/lib/python3.8/site-packages/Cython-3.0.0a10.dist-info/COPYING.txt
./venv/lib/python3.8/site-packages/Cython-3.0.0a10.dist-info/LICENSE.txt
./venv/lib/python3.8/site-packages/Cython-3.0.0a10.dist-info/entry_points.txt
./venv/lib/python3.8/site-packages/Cython-3.0.0a10.dist-info/top_level.txt
./venv/lib/python3.8/site-packages/Cython/Runtime/refnanny.pyx
./venv/lib/python3.8/site-packages/Cython/Utility/CConvert.pyx
./venv/lib/python3.8/site-packages/Cython/Utility/CpdefEnums.pyx
./venv/lib/python3.8/site-packages/Cython/Utility/CppConvert.pyx
./venv/lib/python3.8/site-packages/Cython/Utility/MemoryView.pyx
./venv/lib/python3.8/site-packages/Cython/Utility/TestCyUtilityLoader.pyx
./venv/lib/python3.8/site-packages/Cython/Utility/TestCythonScope.pyx
./venv/lib/python3.8/site-packages/Jinja2-3.1.2.dist-info/entry_points.txt
./venv/lib/python3.8/site-packages/Jinja2-3.1.2.dist-info/top_level.txt
./venv/lib/python3.8/site-packages/MarkupSafe-2.1.1.dist-info/top_level.txt
./venv/lib/python3.8/site-packages/Pillow-9.1.1.dist-info/top_level.txt
./venv/lib/python3.8/site-packages/Pygments-2.12.0.dist-info/entry_points.txt
./venv/lib/python3.8/site-packages/Pygments-2.12.0.dist-info/top_level.txt
./venv/lib/python3.8/site-packages/SecretStorage-3.3.2.dist-info/top_level.txt
./venv/lib/python3.8/site-packages/Sphinx-5.0.1.dist-info/entry_points.txt
./venv/lib/python3.8/site-packages/Sphinx-5.0.1.dist-info/top_level.txt
./venv/lib/python3.8/site-packages/alabaster-0.7.12.dist-info/LICENSE.txt
./venv/lib/python3.8/site-packages/alabaster-0.7.12.dist-info/entry_points.txt
./venv/lib/python3.8/site-packages/alabaster-0.7.12.dist-info/metadata.json
./venv/lib/python3.8/site-packages/alabaster-0.7.12.dist-info/top_level.txt
./venv/lib/python3.8/site-packages/attrs-21.4.0.dist-info/top_level.txt
./venv/lib/python3.8/site-packages/beautifulsoup4-4.11.1.dist-info/top_level.txt
./venv/lib/python3.8/site-packages/bleach-5.0.0.dist-info/top_level.txt
./venv/lib/python3.8/site-packages/bleach/_vendor/vendor.txt
./venv/lib/python3.8/site-packages/bleach/_vendor/html5lib-1.1.dist-info/top_level.txt
./venv/lib/python3.8/site-packages/certifi-2022.5.18.1.dist-info/top_level.txt
./venv/lib/python3.8/site-packages/cffi-1.15.0.dist-info/entry_points.txt
./venv/lib/python3.8/site-packages/cffi-1.15.0.dist-info/top_level.txt
./venv/lib/python3.8/site-packages/charset_normalizer-2.0.12.dist-info/entry_points.txt
./venv/lib/python3.8/site-packages/charset_normalizer-2.0.12.dist-info/top_level.txt
./venv/lib/python3.8/site-packages/commonmark-0.9.1.dist-info/entry_points.txt
./venv/lib/python3.8/site-packages/commonmark-0.9.1.dist-info/top_level.txt
./venv/lib/python3.8/site-packages/cryptography-37.0.2.dist-info/top_level.txt
./venv/lib/python3.8/site-packages/cycler-0.11.0.dist-info/top_level.txt
./venv/lib/python3.8/site-packages/defusedxml-0.7.1.dist-info/top_level.txt
./venv/lib/python3.8/site-packages/docutils-0.17.1.dist-info/COPYING.txt
./venv/lib/python3.8/site-packages/docutils-0.17.1.dist-info/top_level.txt
./venv/lib/python3.8/site-packages/docutils/parsers/rst/include/README.txt
./venv/lib/python3.8/site-packages/docutils/parsers/rst/include/isoamsa.txt
./venv/lib/python3.8/site-packages/docutils/parsers/rst/include/isoamsb.txt
./venv/lib/python3.8/site-packages/docutils/parsers/rst/include/isoamsc.txt
./venv/lib/python3.8/site-packages/docutils/parsers/rst/include/isoamsn.txt
./venv/lib/python3.8/site-packages/docutils/parsers/rst/include/isoamso.txt
./venv/lib/python3.8/site-packages/docutils/parsers/rst/include/isoamsr.txt
./venv/lib/python3.8/site-packages/docutils/parsers/rst/include/isobox.txt
./venv/lib/python3.8/site-packages/docutils/parsers/rst/include/isocyr1.txt
./venv/lib/python3.8/site-packages/docutils/parsers/rst/include/isocyr2.txt
./venv/lib/python3.8/site-packages/docutils/parsers/rst/include/isodia.txt
./venv/lib/python3.8/site-packages/docutils/parsers/rst/include/isogrk1.txt
./venv/lib/python3.8/site-packages/docutils/parsers/rst/include/isogrk2.txt
./venv/lib/python3.8/site-packages/fastjsonschema-2.15.3.dist-info/top_level.txt
./venv/lib/python3.8/site-packages/fonttools-4.33.3.dist-info/entry_points.txt
./venv/lib/python3.8/site-packages/fonttools-4.33.3.dist-info/top_level.txt
./venv/lib/python3.8/site-packages/idna-3.3.dist-info/top_level.txt
./venv/lib/python3.8/site-packages/imagesize-1.3.0.dist-info/top_level.txt
./venv/lib/python3.8/site-packages/importlib_metadata-4.11.4.dist-info/top_level.txt
./venv/lib/python3.8/site-packages/importlib_resources-5.7.1.dist-info/top_level.txt
./venv/lib/python3.8/site-packages/iniconfig-1.1.1.dist-info/top_level.txt
./venv/lib/python3.8/site-packages/jsonschema-4.6.0.dist-info/entry_points.txt
./venv/lib/python3.8/site-packages/jupyter_client-7.3.2.dist-info/entry_points.txt
./venv/lib/python3.8/site-packages/jupyter_core-4.10.0.dist-info/entry_points.txt
./venv/lib/python3.8/site-packages/jupyter_core-4.10.0.dist-info/top_level.txt
./venv/lib/python3.8/site-packages/jupyterlab_pygments-0.2.2.dist-info/top_level.txt
./venv/lib/python3.8/site-packages/keyring-23.5.1.dist-info/entry_points.txt
