Metadata-Version: 2.1
Name: peritus-matrixprofile
Version: 1.1.111
Summary: Fork of An open source time series data mining library based on Matrix Profile algorithms.
Home-page: https://github.com/aiacovella/matrixprofile.git
Author: aiacovella
Author-email: java.peritus@gmail.com
Project-URL: Matrix Profile Foundation, https://matrixprofile.org
Project-URL: Source Code, https://github.com/aiacovella/matrixprofile.git
Keywords: matrix profile time series discord motif analysis data science anomaly pattern
Classifier: Programming Language :: Python :: 2
Classifier: Programming Language :: Python :: 3
Classifier: License :: OSI Approved :: Apache Software License
Classifier: Intended Audience :: Science/Research
Classifier: Intended Audience :: Information Technology
Classifier: Intended Audience :: Developers
Classifier: Operating System :: MacOS
Classifier: Operating System :: Microsoft :: Windows
Classifier: Operating System :: POSIX
Classifier: Topic :: Software Development
Classifier: Topic :: Scientific/Engineering
License-File: LICENSE
